celery_sqlalchemy_kit/__init__.py
celery_sqlalchemy_kit/base_task.py
celery_sqlalchemy_kit/scheduler.py
celery_sqlalchemy_kit/db/__init__.py
celery_sqlalchemy_kit/db/crud.py
celery_sqlalchemy_kit/db/model.py
celery_sqlalchemy_kit/db/session.py
celery_sqlalchemy_kit-0.2.0.dist-info/METADATA
celery_sqlalchemy_kit-0.2.0.dist-info/WHEEL
celery_sqlalchemy_kit-0.2.0.dist-info/licenses/LICENSE
celery_sqlalchemy_kit-0.2.0.dist-info/RECORD
