Metadata-Version: 2.4
Name: celery-sqlalchemy-kit
Version: 0.2.0
Summary: Schedule tasks in an SQL Database and define Async Celery Tasks.
Project-URL: Homepage, https://github.com/cap-on/celery-sqlalchemy-kit
Project-URL: Bug Tracker, https://github.com/cap-on/celery-sqlalchemy-kit/issues
Author-email: Amelie Luecke <amelie.luecke@cap-on.de>, Philipp Ratz <philipp.ratz@cap-on.de>
License-File: LICENSE
Classifier: Development Status :: 3 - Alpha
Classifier: Framework :: Celery
Classifier: License :: OSI Approved :: MIT License
Classifier: Operating System :: OS Independent
Classifier: Programming Language :: Python :: 3
Requires-Python: >=3.10
Requires-Dist: celery<6,>=5.2.7
Requires-Dist: sqlalchemy<3,>=1.4.46
Provides-Extra: broker
Requires-Dist: redis<8,>=4.5.1; extra == 'broker'
Provides-Extra: tests
Requires-Dist: pytest<9,>7.2.1; extra == 'tests'
Requires-Dist: tenacity<10,>=8.1.0; extra == 'tests'
